videopypeline/__init__.py
videopypeline/actions.py
videopypeline/core.py
videopypeline/functions.py
videopypeline/generators.py
videopypeline-0.0.4.dist-info/METADATA
videopypeline-0.0.4.dist-info/WHEEL
videopypeline-0.0.4.dist-info/top_level.txt
videopypeline-0.0.4.dist-info/RECORD
